{
  "categories":{
    "Category":"Category"
  },
  "data":{
    "nodes":[
      {
        "label":"2011款蒙迪欧致胜GTDi240 2.0T豪华运动导航版",
        "value":8,
        "id":15,
        "categories":[
          "Category"
        ],
        "info":"{'name_en': '2011款蒙迪欧致胜GTDi240 2.0T豪华运动导航版', 'name': '2011款蒙迪欧致胜GTDi240 2.0T豪华运动导航版'}"
      },
      {
        "label":"建伟国际汽车城",
        "value":8,
        "id":2320,
        "categories":[
          "Category"
        ],
        "info":"{'name_en': '建伟国际汽车城', 'name': '建伟国际汽车城'}"
      },
      {
        "label":"江淮瑞鹰Ⅱ",
        "value":8,
        "id":10439,
        "categories":[
          "Category"
        ],
        "info":"{'name_en': '江淮瑞鹰Ⅱ', 'name': '江淮瑞鹰Ⅱ'}"
      },
      {
        "label":"蚌埠市宝驰之星汽车修理厂",
        "value":8,
        "id":6182,
        "categories":[
          "Category"
        ],
        "info":"{'name_en': '蚌埠市宝驰之星汽车修理厂', 'name': '蚌埠市宝驰之星汽车修理厂'}"
      },
      {
        "label":"CS7 Velocity",
        "value":8,
        "id":7888,
        "categories":[
          "Category"
        ],
        "info":"{'name_en': 'CS7 Velocity', 'name': 'CS7 Velocity'}"
      },
      {
        "label":"广州国际电子大厦",
        "value":8,
        "id":3596,
        "categories":[
          "Category"
        ],
        "info":"{'name_en': '广州国际电子大厦', 'name': '广州国际电子大厦'}"
      },
      {
        "label":"南疆地洼区",
        "value":8,
        "id":1010,
        "categories":[
          "Category"
        ],
        "info":"{'name_en': '南疆地洼区', 'name': '南疆地洼区'}"
      },
      {
        "label":"和田玉",
        "value":8,
        "id":11944,
        "categories":[
          "Category"
        ],
        "info":"{'name_en': '和田玉', 'name': '和田玉'}"
      },
      {
        "label":"阿夫拉季",
        "value":8,
        "id":6945,
        "categories":[
          "Category"
        ],
        "info":"{'name_en': '阿夫拉季', 'name': '阿夫拉季'}"
      },
      {
        "label":"四山摩崖石刻",
        "value":8,
        "id":10779,
        "categories":[
          "Category"
        ],
        "info":"{'name_en': '四山摩崖石刻', 'name': '四山摩崖石刻'}"
      },
      {
        "label":"达拉特旗石英砂岩矿",
        "value":8,
        "id":6273,
        "categories":[
          "Category"
        ],
        "info":"{'name_en': '达拉特旗石英砂岩矿', 'name': '达拉特旗石英砂岩矿'}"
      },
      {
        "label":"中华碧玉园",
        "value":8,
        "id":10565,
        "categories":[
          "Category"
        ],
        "info":"{'name_en': '中华碧玉园', 'name': '中华碧玉园'}"
      },
      {
        "label":"陆家嘴金融城",
        "value":8,
        "id":6787,
        "categories":[
          "Category"
        ],
        "info":"{'name_en': '陆家嘴金融城', 'name': '陆家嘴金融城'}"
      },
      {
        "label":"金融创新",
        "value":8,
        "id":11543,
        "categories":[
          "Category"
        ],
        "info":"{'name_en': '金融创新', 'name': '金融创新'}"
      },
      {
        "label":"乌塞廖父子酒庄",
        "value":8,
        "id":7490,
        "categories":[
          "Category"
        ],
        "info":"{'name_en': '乌塞廖父子酒庄', 'name': '乌塞廖父子酒庄'}"
      },
      {
        "label":"拉菲纳",
        "value":8,
        "id":7886,
        "categories":[
          "Category"
        ],
        "info":"{'name_en': '拉菲纳', 'name': '拉菲纳'}"
      },
      {
        "label":"赤子香",
        "value":8,
        "id":1623,
        "categories":[
          "Category"
        ],
        "info":"{'name_en': '赤子香', 'name': '赤子香'}"
      },
      {
        "label":"兰陵荀子文化园",
        "value":8,
        "id":8286,
        "categories":[
          "Category"
        ],
        "info":"{'name_en': '兰陵荀子文化园', 'name': '兰陵荀子文化园'}"
      },
      {
        "label":"巴颜喀拉地洼区",
        "value":8,
        "id":8822,
        "categories":[
          "Category"
        ],
        "info":"{'name_en': '巴颜喀拉地洼区', 'name': '巴颜喀拉地洼区'}"
      },
      {
        "label":"海口市气象局",
        "value":8,
        "id":3286,
        "categories":[
          "Category"
        ],
        "info":"{'name_en': '海口市气象局', 'name': '海口市气象局'}"
      },
      {
        "label":"巨龙湖",
        "value":8,
        "id":4768,
        "categories":[
          "Category"
        ],
        "info":"{'name_en': '巨龙湖', 'name': '巨龙湖'}"
      },
      {
        "label":"钦莲",
        "value":8,
        "id":7426,
        "categories":[
          "Category"
        ],
        "info":"{'name_en': '钦莲', 'name': '钦莲'}"
      },
      {
        "label":"西安巨坤花卉中心",
        "value":8,
        "id":5856,
        "categories":[
          "Category"
        ],
        "info":"{'name_en': '西安巨坤花卉中心', 'name': '西安巨坤花卉中心'}"
      },
      {
        "label":"花溪区招商引资局",
        "value":8,
        "id":3201,
        "categories":[
          "Category"
        ],
        "info":"{'name_en': '花溪区招商引资局', 'name': '花溪区招商引资局'}"
      },
      {
        "label":"螺丝山景区",
        "value":8,
        "id":997,
        "categories":[
          "Category"
        ],
        "info":"{'name_en': '螺丝山景区', 'name': '螺丝山景区'}"
      },
      {
        "label":"撤丁硕石纹",
        "value":8,
        "id":1133,
        "categories":[
          "Category"
        ],
        "info":"{'name_en': '撤丁硕石纹', 'name': '撤丁硕石纹'}"
      },
      {
        "label":"天隆珠宝行",
        "value":8,
        "id":3255,
        "categories":[
          "Category"
        ],
        "info":"{'name_en': '天隆珠宝行', 'name': '天隆珠宝行'}"
      },
      {
        "label":"糜岭梁",
        "value":8,
        "id":6249,
        "categories":[
          "Category"
        ],
        "info":"{'name_en': '糜岭梁', 'name': '糜岭梁'}"
      },
      {
        "label":"香椿茶",
        "value":8,
        "id":7246,
        "categories":[
          "Category"
        ],
        "info":"{'name_en': '香椿茶', 'name': '香椿茶'}"
      },
      {
        "label":"得白村",
        "value":8,
        "id":7280,
        "categories":[
          "Category"
        ],
        "info":"{'name_en': '得白村', 'name': '得白村'}"
      },
      {
        "label":"四王府社区",
        "value":8,
        "id":9600,
        "categories":[
          "Category"
        ],
        "info":"{'name_en': '四王府社区', 'name': '四王府社区'}"
      },
      {
        "label":"宁兴城市广场",
        "value":8,
        "id":2119,
        "categories":[
          "Category"
        ],
        "info":"{'name_en': '宁兴城市广场', 'name': '宁兴城市广场'}"
      },
      {
        "label":"祖红渔家乐",
        "value":8,
        "id":2539,
        "categories":[
          "Category"
        ],
        "info":"{'name_en': '祖红渔家乐', 'name': '祖红渔家乐'}"
      },
      {
        "label":"位置区码",
        "value":8,
        "id":8151,
        "categories":[
          "Category"
        ],
        "info":"{'name_en': '位置区码', 'name': '位置区码'}"
      },
      {
        "label":"盘龙垴",
        "value":8,
        "id":5277,
        "categories":[
          "Category"
        ],
        "info":"{'name_en': '盘龙垴', 'name': '盘龙垴'}"
      },
      {
        "label":"窄坡尖",
        "value":8,
        "id":3602,
        "categories":[
          "Category"
        ],
        "info":"{'name_en': '窄坡尖', 'name': '窄坡尖'}"
      },
      {
        "label":"张家口市瑞源口蘑有限责任公司",
        "value":8,
        "id":5281,
        "categories":[
          "Category"
        ],
        "info":"{'name_en': '张家口市瑞源口蘑有限责任公司', 'name': '张家口市瑞源口蘑有限责任公司'}"
      },
      {
        "label":"引洮工程",
        "value":8,
        "id":2721,
        "categories":[
          "Category"
        ],
        "info":"{'name_en': '引洮工程', 'name': '引洮工程'}"
      },
      {
        "label":"谢涅日湖",
        "value":8,
        "id":10856,
        "categories":[
          "Category"
        ],
        "info":"{'name_en': '谢涅日湖', 'name': '谢涅日湖'}"
      },
      {
        "label":"塔坪寺",
        "value":8,
        "id":5297,
        "categories":[
          "Category"
        ],
        "info":"{'name_en': '塔坪寺', 'name': '塔坪寺'}"
      },
      {
        "label":"鸾凤春树图",
        "value":8,
        "id":6837,
        "categories":[
          "Category"
        ],
        "info":"{'name_en': '鸾凤春树图', 'name': '鸾凤春树图'}"
      },
      {
        "label":"长肉剂",
        "value":8,
        "id":7915,
        "categories":[
          "Category"
        ],
        "info":"{'name_en': '长肉剂', 'name': '长肉剂'}"
      },
      {
        "label":"小汤山现代农业示范园区",
        "value":8,
        "id":6093,
        "categories":[
          "Category"
        ],
        "info":"{'name_en': '小汤山现代农业示范园区', 'name': '小汤山现代农业示范园区'}"
      },
      {
        "label":"香格里拉五凤山",
        "value":8,
        "id":2429,
        "categories":[
          "Category"
        ],
        "info":"{'name_en': '香格里拉五凤山', 'name': '香格里拉五凤山'}"
      },
      {
        "label":"金钱山",
        "value":8,
        "id":9214,
        "categories":[
          "Category"
        ],
        "info":"{'name_en': '金钱山', 'name': '金钱山'}"
      },
      {
        "label":"石家庄铭升动力汽车改装店",
        "value":8,
        "id":11379,
        "categories":[
          "Category"
        ],
        "info":"{'name_en': '石家庄铭升动力汽车改装店', 'name': '石家庄铭升动力汽车改装店'}"
      },
      {
        "label":"海底彩带",
        "value":8,
        "id":9227,
        "categories":[
          "Category"
        ],
        "info":"{'name_en': '海底彩带', 'name': '海底彩带'}"
      },
      {
        "label":"四方灵泉",
        "value":8,
        "id":4412,
        "categories":[
          "Category"
        ],
        "info":"{'name_en': '四方灵泉', 'name': '四方灵泉'}"
      },
      {
        "label":"剑阁县国有资产监督管理局",
        "value":8,
        "id":11180,
        "categories":[
          "Category"
        ],
        "info":"{'name_en': '剑阁县国有资产监督管理局', 'name': '剑阁县国有资产监督管理局'}"
      },
      {
        "label":"中国科学院资源环境科学信息中心酒泉地区信息工作站",
        "value":8,
        "id":7694,
        "categories":[
          "Category"
        ],
        "info":"{'name_en': '中国科学院资源环境科学信息中心酒泉地区信息工作站', 'name': '中国科学院资源环境科学信息中心酒泉地区信息工作站'}"
      },
      {
        "label":"凤凰铺",
        "value":8,
        "id":4700,
        "categories":[
          "Category"
        ],
        "info":"{'name_en': '凤凰铺', 'name': '凤凰铺'}"
      },
      {
        "label":"地沟窑",
        "value":8,
        "id":2580,
        "categories":[
          "Category"
        ],
        "info":"{'name_en': '地沟窑', 'name': '地沟窑'}"
      },
      {
        "label":"玉科草原",
        "value":8,
        "id":3155,
        "categories":[
          "Category"
        ],
        "info":"{'name_en': '玉科草原', 'name': '玉科草原'}"
      },
      {
        "label":"横桥崖画",
        "value":8,
        "id":1815,
        "categories":[
          "Category"
        ],
        "info":"{'name_en': '横桥崖画', 'name': '横桥崖画'}"
      },
      {
        "label":"爱辉区科学技术与信息产业局",
        "value":8,
        "id":1561,
        "categories":[
          "Category"
        ],
        "info":"{'name_en': '爱辉区科学技术与信息产业局', 'name': '爱辉区科学技术与信息产业局'}"
      },
      {
        "label":"泊子滩",
        "value":8,
        "id":10408,
        "categories":[
          "Category"
        ],
        "info":"{'name_en': '泊子滩', 'name': '泊子滩'}"
      },
      {
        "label":"蒸水",
        "value":8,
        "id":9855,
        "categories":[
          "Category"
        ],
        "info":"{'name_en': '蒸水', 'name': '蒸水'}"
      },
      {
        "label":"如皋龙盛游乐场",
        "value":8,
        "id":886,
        "categories":[
          "Category"
        ],
        "info":"{'name_en': '如皋龙盛游乐场', 'name': '如皋龙盛游乐场'}"
      },
      {
        "label":"姜汁饼人",
        "value":8,
        "id":1416,
        "categories":[
          "Category"
        ],
        "info":"{'name_en': '姜汁饼人', 'name': '姜汁饼人'}"
      },
      {
        "label":"洞天岩",
        "value":8,
        "id":9584,
        "categories":[
          "Category"
        ],
        "info":"{'name_en': '洞天岩', 'name': '洞天岩'}"
      },
      {
        "label":"武威牛家花园",
        "value":8,
        "id":5655,
        "categories":[
          "Category"
        ],
        "info":"{'name_en': '武威牛家花园', 'name': '武威牛家花园'}"
      },
      {
        "label":"玉石驼峰",
        "value":8,
        "id":1986,
        "categories":[
          "Category"
        ],
        "info":"{'name_en': '玉石驼峰', 'name': '玉石驼峰'}"
      },
      {
        "label":"牛仔竞技公园",
        "value":8,
        "id":9093,
        "categories":[
          "Category"
        ],
        "info":"{'name_en': '牛仔竞技公园', 'name': '牛仔竞技公园'}"
      },
      {
        "label":"德莎4980",
        "value":8,
        "id":1558,
        "categories":[
          "Category"
        ],
        "info":"{'name_en': '德莎4980', 'name': '德莎4980'}"
      },
      {
        "label":"信阳集云山",
        "value":8,
        "id":9761,
        "categories":[
          "Category"
        ],
        "info":"{'name_en': '信阳集云山', 'name': '信阳集云山'}"
      },
      {
        "label":"石夫人",
        "value":8,
        "id":2675,
        "categories":[
          "Category"
        ],
        "info":"{'name_en': '石夫人', 'name': '石夫人'}"
      },
      {
        "label":"长葛站",
        "value":8,
        "id":7234,
        "categories":[
          "Category"
        ],
        "info":"{'name_en': '长葛站', 'name': '长葛站'}"
      },
      {
        "label":"千里相会",
        "value":8,
        "id":5900,
        "categories":[
          "Category"
        ],
        "info":"{'name_en': '千里相会', 'name': '千里相会'}"
      },
      {
        "label":"高尔基故居",
        "value":8,
        "id":1983,
        "categories":[
          "Category"
        ],
        "info":"{'name_en': '高尔基故居', 'name': '高尔基故居'}"
      },
      {
        "label":"莽山森林温泉",
        "value":8,
        "id":1747,
        "categories":[
          "Category"
        ],
        "info":"{'name_en': '莽山森林温泉', 'name': '莽山森林温泉'}"
      },
      {
        "label":"中国现代五项赛事中心",
        "value":8,
        "id":10163,
        "categories":[
          "Category"
        ],
        "info":"{'name_en': '中国现代五项赛事中心', 'name': '中国现代五项赛事中心'}"
      },
      {
        "label":"龙泉湖森林公园",
        "value":8,
        "id":8496,
        "categories":[
          "Category"
        ],
        "info":"{'name_en': '龙泉湖森林公园', 'name': '龙泉湖森林公园'}"
      },
      {
        "label":"锦州帽山",
        "value":8,
        "id":9368,
        "categories":[
          "Category"
        ],
        "info":"{'name_en': '锦州帽山', 'name': '锦州帽山'}"
      },
      {
        "label":"铜龙河",
        "value":8,
        "id":175,
        "categories":[
          "Category"
        ],
        "info":"{'name_en': '铜龙河', 'name': '铜龙河'}"
      },
      {
        "label":"户冢站",
        "value":8,
        "id":4642,
        "categories":[
          "Category"
        ],
        "info":"{'name_en': '户冢站', 'name': '户冢站'}"
      },
      {
        "label":"加勒拉斯火山",
        "value":8,
        "id":11220,
        "categories":[
          "Category"
        ],
        "info":"{'name_en': '加勒拉斯火山', 'name': '加勒拉斯火山'}"
      },
      {
        "label":"徐闻文化广场",
        "value":8,
        "id":9158,
        "categories":[
          "Category"
        ],
        "info":"{'name_en': '徐闻文化广场', 'name': '徐闻文化广场'}"
      },
      {
        "label":"赛影",
        "value":8,
        "id":712,
        "categories":[
          "Category"
        ],
        "info":"{'name_en': '赛影', 'name': '赛影'}"
      },
      {
        "label":"德钦大宝寺",
        "value":8,
        "id":1214,
        "categories":[
          "Category"
        ],
        "info":"{'name_en': '德钦大宝寺', 'name': '德钦大宝寺'}"
      },
      {
        "label":"石家河",
        "value":8,
        "id":11089,
        "categories":[
          "Category"
        ],
        "info":"{'name_en': '石家河', 'name': '石家河'}"
      },
      {
        "label":"古马拉河",
        "value":8,
        "id":6192,
        "categories":[
          "Category"
        ],
        "info":"{'name_en': '古马拉河', 'name': '古马拉河'}"
      },
      {
        "label":"黄台发电厂",
        "value":8,
        "id":7560,
        "categories":[
          "Category"
        ],
        "info":"{'name_en': '黄台发电厂', 'name': '黄台发电厂'}"
      },
      {
        "label":"散花坞",
        "value":8,
        "id":2409,
        "categories":[
          "Category"
        ],
        "info":"{'name_en': '散花坞', 'name': '散花坞'}"
      },
      {
        "label":"前邵集村",
        "value":8,
        "id":10471,
        "categories":[
          "Category"
        ],
        "info":"{'name_en': '前邵集村', 'name': '前邵集村'}"
      },
      {
        "label":"波廉面包店",
        "value":8,
        "id":10529,
        "categories":[
          "Category"
        ],
        "info":"{'name_en': '波廉面包店', 'name': '波廉面包店'}"
      },
      {
        "label":"怀安遗址",
        "value":8,
        "id":6215,
        "categories":[
          "Category"
        ],
        "info":"{'name_en': '怀安遗址', 'name': '怀安遗址'}"
      },
      {
        "label":"嘉兴清真古寺",
        "value":8,
        "id":10120,
        "categories":[
          "Category"
        ],
        "info":"{'name_en': '嘉兴清真古寺', 'name': '嘉兴清真古寺'}"
      },
      {
        "label":"凉风垭站",
        "value":8,
        "id":9341,
        "categories":[
          "Category"
        ],
        "info":"{'name_en': '凉风垭站', 'name': '凉风垭站'}"
      },
      {
        "label":"安陵站",
        "value":8,
        "id":3902,
        "categories":[
          "Category"
        ],
        "info":"{'name_en': '安陵站', 'name': '安陵站'}"
      },
      {
        "label":"丰乳肥臀雕塑",
        "value":8,
        "id":3291,
        "categories":[
          "Category"
        ],
        "info":"{'name_en': '丰乳肥臀雕塑', 'name': '丰乳肥臀雕塑'}"
      },
      {
        "label":"长春鼎盛塑料厂",
        "value":8,
        "id":1059,
        "categories":[
          "Category"
        ],
        "info":"{'name_en': '长春鼎盛塑料厂', 'name': '长春鼎盛塑料厂'}"
      },
      {
        "label":"老隍城传统锅魁",
        "value":8,
        "id":3561,
        "categories":[
          "Category"
        ],
        "info":"{'name_en': '老隍城传统锅魁', 'name': '老隍城传统锅魁'}"
      },
      {
        "label":"巨泉村",
        "value":8,
        "id":5710,
        "categories":[
          "Category"
        ],
        "info":"{'name_en': '巨泉村', 'name': '巨泉村'}"
      },
      {
        "label":"闽清县农业局",
        "value":8,
        "id":7925,
        "categories":[
          "Category"
        ],
        "info":"{'name_en': '闽清县农业局', 'name': '闽清县农业局'}"
      },
      {
        "label":"蔡里口村",
        "value":8,
        "id":1497,
        "categories":[
          "Category"
        ],
        "info":"{'name_en': '蔡里口村', 'name': '蔡里口村'}"
      },
      {
        "label":"福州新华都百货",
        "value":8,
        "id":6610,
        "categories":[
          "Category"
        ],
        "info":"{'name_en': '福州新华都百货', 'name': '福州新华都百货'}"
      },
      {
        "label":"湘银金色阳光",
        "value":8,
        "id":2917,
        "categories":[
          "Category"
        ],
        "info":"{'name_en': '湘银金色阳光', 'name': '湘银金色阳光'}"
      },
      {
        "label":"龙溪村古建筑群",
        "value":8,
        "id":9291,
        "categories":[
          "Category"
        ],
        "info":"{'name_en': '龙溪村古建筑群', 'name': '龙溪村古建筑群'}"
      },
      {
        "label":"柳京饭店",
        "value":8,
        "id":4140,
        "categories":[
          "Category"
        ],
        "info":"{'name_en': '柳京饭店', 'name': '柳京饭店'}"
      },
      {
        "label":"栒邑窑",
        "value":8,
        "id":8784,
        "categories":[
          "Category"
        ],
        "info":"{'name_en': '栒邑窑', 'name': '栒邑窑'}"
      },
      {
        "label":"姜桐村",
        "value":8,
        "id":8851,
        "categories":[
          "Category"
        ],
        "info":"{'name_en': '姜桐村', 'name': '姜桐村'}"
      },
      {
        "label":"黄龙溪碧浓居宾馆",
        "value":8,
        "id":1139,
        "categories":[
          "Category"
        ],
        "info":"{'name_en': '黄龙溪碧浓居宾馆', 'name': '黄龙溪碧浓居宾馆'}"
      },
      {
        "label":"G30次",
        "value":8,
        "id":6045,
        "categories":[
          "Category"
        ],
        "info":"{'name_en': 'G30次', 'name': 'G30次'}"
      },
      {
        "label":"泰山赤鳞鱼国家级水产种质资源保护区",
        "value":8,
        "id":7026,
        "categories":[
          "Category"
        ],
        "info":"{'name_en': '泰山赤鳞鱼国家级水产种质资源保护区', 'name': '泰山赤鳞鱼国家级水产种质资源保护区'}"
      },
      {
        "label":"D5169次",
        "value":8,
        "id":547,
        "categories":[
          "Category"
        ],
        "info":"{'name_en': 'D5169次', 'name': 'D5169次'}"
      }
    ],
    "edges":[
      {
        "id":10573,
        "label":"2011款蒙迪欧致胜GTDi240 2.0T豪华运动导航版发布了建伟国际汽车城",
        "from":15,
        "to":2320
      },
      {
        "id":10690,
        "label":"江淮瑞鹰Ⅱ发布了蚌埠市宝驰之星汽车修理厂",
        "from":10439,
        "to":6182
      },
      {
        "id":10922,
        "label":"CS7 Velocity发布了广州国际电子大厦",
        "from":7888,
        "to":3596
      },
      {
        "id":12238,
        "label":"南疆地洼区能够产出和田玉",
        "from":1010,
        "to":11944
      },
      {
        "id":13572,
        "label":"阿夫拉季发布了四山摩崖石刻",
        "from":6945,
        "to":10779
      },
      {
        "id":14471,
        "label":"达拉特旗石英砂岩矿能够产出中华碧玉园",
        "from":6273,
        "to":10565
      },
      {
        "id":14743,
        "label":"陆家嘴金融城发布了金融创新",
        "from":6787,
        "to":11543
      },
      {
        "id":15322,
        "label":"乌塞廖父子酒庄发布了拉菲纳",
        "from":7490,
        "to":7886
      },
      {
        "id":16593,
        "label":"赤子香能够产出兰陵荀子文化园",
        "from":1623,
        "to":8286
      },
      {
        "id":16603,
        "label":"赤子香能够产出巴颜喀拉地洼区",
        "from":1623,
        "to":8822
      },
      {
        "id":16606,
        "label":"赤子香发布了广州国际电子大厦",
        "from":1623,
        "to":3596
      },
      {
        "id":17023,
        "label":"海口市气象局发布了巨龙湖",
        "from":3286,
        "to":4768
      },
      {
        "id":17072,
        "label":"钦莲发布了西安巨坤花卉中心",
        "from":7426,
        "to":5856
      },
      {
        "id":17107,
        "label":"花溪区招商引资局发布了螺丝山景区",
        "from":3201,
        "to":997
      },
      {
        "id":17122,
        "label":"撤丁硕石纹能够产出天隆珠宝行",
        "from":1133,
        "to":3255
      },
      {
        "id":17909,
        "label":"糜岭梁发布了香椿茶",
        "from":6249,
        "to":7246
      },
      {
        "id":17910,
        "label":"香椿茶能够产出得白村",
        "from":7246,
        "to":7280
      },
      {
        "id":17912,
        "label":"香椿茶能够产出四王府社区",
        "from":7246,
        "to":9600
      },
      {
        "id":17914,
        "label":"香椿茶发布了宁兴城市广场",
        "from":7246,
        "to":2119
      },
      {
        "id":17984,
        "label":"祖红渔家乐能够产出位置区码",
        "from":2539,
        "to":8151
      },
      {
        "id":21620,
        "label":"盘龙垴能够产出香椿茶",
        "from":5277,
        "to":7246
      },
      {
        "id":23476,
        "label":"窄坡尖能够产出张家口市瑞源口蘑有限责任公司",
        "from":3602,
        "to":5281
      },
      {
        "id":23832,
        "label":"引洮工程发布了谢涅日湖",
        "from":2721,
        "to":10856
      },
      {
        "id":26825,
        "label":"塔坪寺能够产出鸾凤春树图",
        "from":5297,
        "to":6837
      },
      {
        "id":27160,
        "label":"长肉剂能够产出小汤山现代农业示范园区",
        "from":7915,
        "to":6093
      },
      {
        "id":27162,
        "label":"长肉剂能够产出阿夫拉季",
        "from":7915,
        "to":6945
      },
      {
        "id":27163,
        "label":"长肉剂能够产出香格里拉五凤山",
        "from":7915,
        "to":2429
      },
      {
        "id":27890,
        "label":"金钱山能够产出香椿茶",
        "from":9214,
        "to":7246
      },
      {
        "id":28480,
        "label":"石家庄铭升动力汽车改装店发布了海底彩带",
        "from":11379,
        "to":9227
      },
      {
        "id":28841,
        "label":"四方灵泉能够产出剑阁县国有资产监督管理局",
        "from":4412,
        "to":11180
      },
      {
        "id":28842,
        "label":"四方灵泉发布了中国科学院资源环境科学信息中心酒泉地区信息工作站",
        "from":4412,
        "to":7694
      },
      {
        "id":30531,
        "label":"凤凰铺发布了长肉剂",
        "from":4700,
        "to":7915
      },
      {
        "id":31804,
        "label":"地沟窑能够产出玉科草原",
        "from":2580,
        "to":3155
      },
      {
        "id":32641,
        "label":"横桥崖画发布了爱辉区科学技术与信息产业局",
        "from":1815,
        "to":1561
      },
      {
        "id":33821,
        "label":"泊子滩发布了蒸水",
        "from":10408,
        "to":9855
      },
      {
        "id":34834,
        "label":"如皋龙盛游乐场能够产出姜汁饼人",
        "from":886,
        "to":1416
      },
      {
        "id":34854,
        "label":"洞天岩发布了鸾凤春树图",
        "from":9584,
        "to":6837
      },
      {
        "id":35359,
        "label":"武威牛家花园发布了玉石驼峰",
        "from":5655,
        "to":1986
      },
      {
        "id":35636,
        "label":"牛仔竞技公园发布了德莎4980",
        "from":9093,
        "to":1558
      },
      {
        "id":35748,
        "label":"塔坪寺发布了鸾凤春树图",
        "from":5297,
        "to":6837
      },
      {
        "id":36007,
        "label":"长肉剂能够产出信阳集云山",
        "from":7915,
        "to":9761
      },
      {
        "id":36008,
        "label":"长肉剂发布了阿夫拉季",
        "from":7915,
        "to":6945
      },
      {
        "id":36934,
        "label":"石夫人发布了鸾凤春树图",
        "from":2675,
        "to":6837
      },
      {
        "id":40137,
        "label":"长葛站发布了千里相会",
        "from":7234,
        "to":5900
      },
      {
        "id":42743,
        "label":"高尔基故居发布了德莎4980",
        "from":1983,
        "to":1558
      },
      {
        "id":43106,
        "label":"莽山森林温泉能够产出赤子香",
        "from":1747,
        "to":1623
      },
      {
        "id":44099,
        "label":"德莎4980能够产出中国现代五项赛事中心",
        "from":1558,
        "to":10163
      },
      {
        "id":44101,
        "label":"德莎4980发布了龙泉湖森林公园",
        "from":1558,
        "to":8496
      },
      {
        "id":44102,
        "label":"德莎4980发布了锦州帽山",
        "from":1558,
        "to":9368
      },
      {
        "id":44105,
        "label":"德莎4980发布了铜龙河",
        "from":1558,
        "to":175
      },
      {
        "id":44110,
        "label":"德莎4980发布了牛仔竞技公园",
        "from":1558,
        "to":9093
      },
      {
        "id":44111,
        "label":"德莎4980发布了户冢站",
        "from":1558,
        "to":4642
      },
      {
        "id":44114,
        "label":"德莎4980发布了加勒拉斯火山",
        "from":1558,
        "to":11220
      },
      {
        "id":44117,
        "label":"德莎4980发布了徐闻文化广场",
        "from":1558,
        "to":9158
      },
      {
        "id":44850,
        "label":"赛影发布了德钦大宝寺",
        "from":712,
        "to":1214
      },
      {
        "id":44977,
        "label":"石家河发布了鸾凤春树图",
        "from":11089,
        "to":6837
      },
      {
        "id":45321,
        "label":"古马拉河发布了黄台发电厂",
        "from":6192,
        "to":7560
      },
      {
        "id":45915,
        "label":"散花坞能够产出蒸水",
        "from":2409,
        "to":9855
      },
      {
        "id":45917,
        "label":"蒸水能够产出前邵集村",
        "from":9855,
        "to":10471
      },
      {
        "id":45919,
        "label":"蒸水能够产出波廉面包店",
        "from":9855,
        "to":10529
      },
      {
        "id":45921,
        "label":"蒸水能够产出怀安遗址",
        "from":9855,
        "to":6215
      },
      {
        "id":45923,
        "label":"嘉兴清真古寺发布了蒸水",
        "from":10120,
        "to":9855
      },
      {
        "id":45925,
        "label":"蒸水发布了凉风垭站",
        "from":9855,
        "to":9341
      },
      {
        "id":46376,
        "label":"安陵站发布了达拉特旗石英砂岩矿",
        "from":3902,
        "to":6273
      },
      {
        "id":47766,
        "label":"丰乳肥臀雕塑发布了长春鼎盛塑料厂",
        "from":3291,
        "to":1059
      },
      {
        "id":48317,
        "label":"老隍城传统锅魁能够产出巨泉村",
        "from":3561,
        "to":5710
      },
      {
        "id":48320,
        "label":"老隍城传统锅魁发布了闽清县农业局",
        "from":3561,
        "to":7925
      },
      {
        "id":48323,
        "label":"老隍城传统锅魁发布了蔡里口村",
        "from":3561,
        "to":1497
      },
      {
        "id":48506,
        "label":"福州新华都百货发布了德莎4980",
        "from":6610,
        "to":1558
      },
      {
        "id":48872,
        "label":"湘银金色阳光能够产出龙溪村古建筑群",
        "from":2917,
        "to":9291
      },
      {
        "id":49617,
        "label":"张家口市瑞源口蘑有限责任公司发布了柳京饭店",
        "from":5281,
        "to":4140
      },
      {
        "id":49618,
        "label":"栒邑窑能够产出张家口市瑞源口蘑有限责任公司",
        "from":8784,
        "to":5281
      },
      {
        "id":49620,
        "label":"张家口市瑞源口蘑有限责任公司能够产出姜桐村",
        "from":5281,
        "to":8851
      },
      {
        "id":49687,
        "label":"黄龙溪碧浓居宾馆发布了香椿茶",
        "from":1139,
        "to":7246
      },
      {
        "id":51862,
        "label":"乌塞廖父子酒庄发布了G30次",
        "from":7490,
        "to":6045
      },
      {
        "id":51898,
        "label":"泰山赤鳞鱼国家级水产种质资源保护区能够产出D5169次",
        "from":7026,
        "to":547
      }
    ]
  }
}