{
  "categories":{
    "Category":"Category"
  },
  "data":{
    "nodes":[
      {
        "label":"街区路",
        "value":9,
        "id":3172,
        "categories":[
          "Category"
        ],
        "info":"{'name_en': '街区路', 'name': '街区路'}"
      },
      {
        "label":"国际通大街",
        "value":9,
        "id":9434,
        "categories":[
          "Category"
        ],
        "info":"{'name_en': '国际通大街', 'name': '国际通大街'}"
      },
      {
        "label":"三弓路",
        "value":9,
        "id":5462,
        "categories":[
          "Category"
        ],
        "info":"{'name_en': '三弓路', 'name': '三弓路'}"
      },
      {
        "label":"六条站",
        "value":9,
        "id":8149,
        "categories":[
          "Category"
        ],
        "info":"{'name_en': '六条站', 'name': '六条站'}"
      },
      {
        "label":"黑山东区社区",
        "value":9,
        "id":9270,
        "categories":[
          "Category"
        ],
        "info":"{'name_en': '黑山东区社区', 'name': '黑山东区社区'}"
      },
      {
        "label":"昆曼大通道",
        "value":9,
        "id":3987,
        "categories":[
          "Category"
        ],
        "info":"{'name_en': '昆曼大通道', 'name': '昆曼大通道'}"
      },
      {
        "label":"下牛街",
        "value":9,
        "id":1444,
        "categories":[
          "Category"
        ],
        "info":"{'name_en': '下牛街', 'name': '下牛街'}"
      },
      {
        "label":"徐洲新村",
        "value":9,
        "id":9539,
        "categories":[
          "Category"
        ],
        "info":"{'name_en': '徐洲新村', 'name': '徐洲新村'}"
      },
      {
        "label":"三洞桥社区",
        "value":9,
        "id":4860,
        "categories":[
          "Category"
        ],
        "info":"{'name_en': '三洞桥社区', 'name': '三洞桥社区'}"
      },
      {
        "label":"龙舟社区",
        "value":9,
        "id":235,
        "categories":[
          "Category"
        ],
        "info":"{'name_en': '龙舟社区', 'name': '龙舟社区'}"
      },
      {
        "label":"桂苑城市花园",
        "value":9,
        "id":8087,
        "categories":[
          "Category"
        ],
        "info":"{'name_en': '桂苑城市花园', 'name': '桂苑城市花园'}"
      },
      {
        "label":"龙霄社区",
        "value":9,
        "id":1641,
        "categories":[
          "Category"
        ],
        "info":"{'name_en': '龙霄社区', 'name': '龙霄社区'}"
      },
      {
        "label":"八建线",
        "value":9,
        "id":8040,
        "categories":[
          "Category"
        ],
        "info":"{'name_en': '八建线', 'name': '八建线'}"
      },
      {
        "label":"张家界十字街",
        "value":9,
        "id":4934,
        "categories":[
          "Category"
        ],
        "info":"{'name_en': '张家界十字街', 'name': '张家界十字街'}"
      },
      {
        "label":"湖东路",
        "value":9,
        "id":3095,
        "categories":[
          "Category"
        ],
        "info":"{'name_en': '湖东路', 'name': '湖东路'}"
      },
      {
        "label":"东花墙子街",
        "value":9,
        "id":6400,
        "categories":[
          "Category"
        ],
        "info":"{'name_en': '东花墙子街', 'name': '东花墙子街'}"
      },
      {
        "label":"东川路",
        "value":9,
        "id":1944,
        "categories":[
          "Category"
        ],
        "info":"{'name_en': '东川路', 'name': '东川路'}"
      },
      {
        "label":"太平北路",
        "value":9,
        "id":7042,
        "categories":[
          "Category"
        ],
        "info":"{'name_en': '太平北路', 'name': '太平北路'}"
      },
      {
        "label":"风景路",
        "value":9,
        "id":5104,
        "categories":[
          "Category"
        ],
        "info":"{'name_en': '风景路', 'name': '风景路'}"
      },
      {
        "label":"杨树浦路",
        "value":9,
        "id":8056,
        "categories":[
          "Category"
        ],
        "info":"{'name_en': '杨树浦路', 'name': '杨树浦路'}"
      },
      {
        "label":"春秋大道",
        "value":9,
        "id":8275,
        "categories":[
          "Category"
        ],
        "info":"{'name_en': '春秋大道', 'name': '春秋大道'}"
      },
      {
        "label":"机车西社区",
        "value":9,
        "id":4753,
        "categories":[
          "Category"
        ],
        "info":"{'name_en': '机车西社区', 'name': '机车西社区'}"
      },
      {
        "label":"京通快速",
        "value":9,
        "id":1955,
        "categories":[
          "Category"
        ],
        "info":"{'name_en': '京通快速', 'name': '京通快速'}"
      },
      {
        "label":"旅馆街",
        "value":9,
        "id":6048,
        "categories":[
          "Category"
        ],
        "info":"{'name_en': '旅馆街', 'name': '旅馆街'}"
      },
      {
        "label":"九寨沟格桑宾馆",
        "value":9,
        "id":9153,
        "categories":[
          "Category"
        ],
        "info":"{'name_en': '九寨沟格桑宾馆', 'name': '九寨沟格桑宾馆'}"
      },
      {
        "label":"漆咸道",
        "value":9,
        "id":10923,
        "categories":[
          "Category"
        ],
        "info":"{'name_en': '漆咸道', 'name': '漆咸道'}"
      },
      {
        "label":"重庆磁器口明清商业街",
        "value":9,
        "id":224,
        "categories":[
          "Category"
        ],
        "info":"{'name_en': '重庆磁器口明清商业街', 'name': '重庆磁器口明清商业街'}"
      },
      {
        "label":"调顺路",
        "value":9,
        "id":656,
        "categories":[
          "Category"
        ],
        "info":"{'name_en': '调顺路', 'name': '调顺路'}"
      },
      {
        "label":"钟楼街",
        "value":9,
        "id":8595,
        "categories":[
          "Category"
        ],
        "info":"{'name_en': '钟楼街', 'name': '钟楼街'}"
      },
      {
        "label":"柳市街",
        "value":9,
        "id":4315,
        "categories":[
          "Category"
        ],
        "info":"{'name_en': '柳市街', 'name': '柳市街'}"
      },
      {
        "label":"双胜街",
        "value":9,
        "id":1241,
        "categories":[
          "Category"
        ],
        "info":"{'name_en': '双胜街', 'name': '双胜街'}"
      },
      {
        "label":"千福巷",
        "value":9,
        "id":3140,
        "categories":[
          "Category"
        ],
        "info":"{'name_en': '千福巷', 'name': '千福巷'}"
      },
      {
        "label":"戏楼胡同",
        "value":9,
        "id":3169,
        "categories":[
          "Category"
        ],
        "info":"{'name_en': '戏楼胡同', 'name': '戏楼胡同'}"
      },
      {
        "label":"枣儿店胡同",
        "value":9,
        "id":600,
        "categories":[
          "Category"
        ],
        "info":"{'name_en': '枣儿店胡同', 'name': '枣儿店胡同'}"
      },
      {
        "label":"青岛科技街",
        "value":9,
        "id":3947,
        "categories":[
          "Category"
        ],
        "info":"{'name_en': '青岛科技街', 'name': '青岛科技街'}"
      },
      {
        "label":"罗布森大街",
        "value":9,
        "id":6967,
        "categories":[
          "Category"
        ],
        "info":"{'name_en': '罗布森大街', 'name': '罗布森大街'}"
      },
      {
        "label":"西藏中路",
        "value":9,
        "id":4989,
        "categories":[
          "Category"
        ],
        "info":"{'name_en': '西藏中路', 'name': '西藏中路'}"
      },
      {
        "label":"成新蒲快速路",
        "value":9,
        "id":6330,
        "categories":[
          "Category"
        ],
        "info":"{'name_en': '成新蒲快速路', 'name': '成新蒲快速路'}"
      },
      {
        "label":"夏悫道",
        "value":9,
        "id":10909,
        "categories":[
          "Category"
        ],
        "info":"{'name_en': '夏悫道', 'name': '夏悫道'}"
      },
      {
        "label":"彩屯街道办事处",
        "value":9,
        "id":790,
        "categories":[
          "Category"
        ],
        "info":"{'name_en': '彩屯街道办事处', 'name': '彩屯街道办事处'}"
      },
      {
        "label":"大厝街",
        "value":9,
        "id":849,
        "categories":[
          "Category"
        ],
        "info":"{'name_en': '大厝街', 'name': '大厝街'}"
      },
      {
        "label":"鼓山路",
        "value":9,
        "id":9484,
        "categories":[
          "Category"
        ],
        "info":"{'name_en': '鼓山路', 'name': '鼓山路'}"
      },
      {
        "label":"花街",
        "value":9,
        "id":8907,
        "categories":[
          "Category"
        ],
        "info":"{'name_en': '花街', 'name': '花街'}"
      },
      {
        "label":"九谷町",
        "value":9,
        "id":751,
        "categories":[
          "Category"
        ],
        "info":"{'name_en': '九谷町', 'name': '九谷町'}"
      },
      {
        "label":"包河社区",
        "value":9,
        "id":7610,
        "categories":[
          "Category"
        ],
        "info":"{'name_en': '包河社区', 'name': '包河社区'}"
      },
      {
        "label":"岳化社区",
        "value":9,
        "id":921,
        "categories":[
          "Category"
        ],
        "info":"{'name_en': '岳化社区', 'name': '岳化社区'}"
      },
      {
        "label":"戴家胡同",
        "value":9,
        "id":4281,
        "categories":[
          "Category"
        ],
        "info":"{'name_en': '戴家胡同', 'name': '戴家胡同'}"
      },
      {
        "label":"塔前街",
        "value":9,
        "id":2876,
        "categories":[
          "Category"
        ],
        "info":"{'name_en': '塔前街', 'name': '塔前街'}"
      },
      {
        "label":"蓬水公路",
        "value":9,
        "id":7491,
        "categories":[
          "Category"
        ],
        "info":"{'name_en': '蓬水公路', 'name': '蓬水公路'}"
      },
      {
        "label":"西门岗古街",
        "value":9,
        "id":7401,
        "categories":[
          "Category"
        ],
        "info":"{'name_en': '西门岗古街', 'name': '西门岗古街'}"
      },
      {
        "label":"绸市街",
        "value":9,
        "id":9044,
        "categories":[
          "Category"
        ],
        "info":"{'name_en': '绸市街', 'name': '绸市街'}"
      },
      {
        "label":"淄峨路",
        "value":9,
        "id":1804,
        "categories":[
          "Category"
        ],
        "info":"{'name_en': '淄峨路', 'name': '淄峨路'}"
      },
      {
        "label":"南三路",
        "value":9,
        "id":9854,
        "categories":[
          "Category"
        ],
        "info":"{'name_en': '南三路', 'name': '南三路'}"
      },
      {
        "label":"夏店路",
        "value":9,
        "id":9565,
        "categories":[
          "Category"
        ],
        "info":"{'name_en': '夏店路', 'name': '夏店路'}"
      },
      {
        "label":"龙王线",
        "value":9,
        "id":5750,
        "categories":[
          "Category"
        ],
        "info":"{'name_en': '龙王线', 'name': '龙王线'}"
      },
      {
        "label":"济新公路",
        "value":9,
        "id":6508,
        "categories":[
          "Category"
        ],
        "info":"{'name_en': '济新公路', 'name': '济新公路'}"
      },
      {
        "label":"舜玉路",
        "value":9,
        "id":1678,
        "categories":[
          "Category"
        ],
        "info":"{'name_en': '舜玉路', 'name': '舜玉路'}"
      },
      {
        "label":"一得街",
        "value":9,
        "id":10360,
        "categories":[
          "Category"
        ],
        "info":"{'name_en': '一得街', 'name': '一得街'}"
      },
      {
        "label":"长丰街办事处",
        "value":9,
        "id":9515,
        "categories":[
          "Category"
        ],
        "info":"{'name_en': '长丰街办事处', 'name': '长丰街办事处'}"
      },
      {
        "label":"龙口市司法局",
        "value":9,
        "id":6280,
        "categories":[
          "Category"
        ],
        "info":"{'name_en': '龙口市司法局', 'name': '龙口市司法局'}"
      },
      {
        "label":"中法家属院",
        "value":9,
        "id":7046,
        "categories":[
          "Category"
        ],
        "info":"{'name_en': '中法家属院', 'name': '中法家属院'}"
      },
      {
        "label":"北15线",
        "value":9,
        "id":11247,
        "categories":[
          "Category"
        ],
        "info":"{'name_en': '北15线', 'name': '北15线'}"
      },
      {
        "label":"北105线",
        "value":9,
        "id":8778,
        "categories":[
          "Category"
        ],
        "info":"{'name_en': '北105线', 'name': '北105线'}"
      },
      {
        "label":"草滩社区",
        "value":9,
        "id":1557,
        "categories":[
          "Category"
        ],
        "info":"{'name_en': '草滩社区', 'name': '草滩社区'}"
      },
      {
        "label":"井涝公路",
        "value":9,
        "id":1356,
        "categories":[
          "Category"
        ],
        "info":"{'name_en': '井涝公路', 'name': '井涝公路'}"
      },
      {
        "label":"大李公路",
        "value":9,
        "id":1591,
        "categories":[
          "Category"
        ],
        "info":"{'name_en': '大李公路', 'name': '大李公路'}"
      },
      {
        "label":"东康庄公路",
        "value":9,
        "id":765,
        "categories":[
          "Category"
        ],
        "info":"{'name_en': '东康庄公路', 'name': '东康庄公路'}"
      },
      {
        "label":"成贤街",
        "value":9,
        "id":3341,
        "categories":[
          "Category"
        ],
        "info":"{'name_en': '成贤街', 'name': '成贤街'}"
      },
      {
        "label":"沙丘路",
        "value":9,
        "id":6115,
        "categories":[
          "Category"
        ],
        "info":"{'name_en': '沙丘路', 'name': '沙丘路'}"
      },
      {
        "label":"白虎山西路",
        "value":9,
        "id":6001,
        "categories":[
          "Category"
        ],
        "info":"{'name_en': '白虎山西路', 'name': '白虎山西路'}"
      },
      {
        "label":"棉花市街",
        "value":9,
        "id":7744,
        "categories":[
          "Category"
        ],
        "info":"{'name_en': '棉花市街', 'name': '棉花市街'}"
      },
      {
        "label":"章索公路",
        "value":9,
        "id":3192,
        "categories":[
          "Category"
        ],
        "info":"{'name_en': '章索公路', 'name': '章索公路'}"
      },
      {
        "label":"香同公路",
        "value":9,
        "id":1126,
        "categories":[
          "Category"
        ],
        "info":"{'name_en': '香同公路', 'name': '香同公路'}"
      },
      {
        "label":"花苑街",
        "value":9,
        "id":9915,
        "categories":[
          "Category"
        ],
        "info":"{'name_en': '花苑街', 'name': '花苑街'}"
      },
      {
        "label":"谷物市场街",
        "value":9,
        "id":11131,
        "categories":[
          "Category"
        ],
        "info":"{'name_en': '谷物市场街', 'name': '谷物市场街'}"
      },
      {
        "label":"北大屿山公路",
        "value":9,
        "id":1248,
        "categories":[
          "Category"
        ],
        "info":"{'name_en': '北大屿山公路', 'name': '北大屿山公路'}"
      },
      {
        "label":"对关街",
        "value":9,
        "id":3,
        "categories":[
          "Category"
        ],
        "info":"{'name_en': '对关街', 'name': '对关街'}"
      },
      {
        "label":"麟祥南街",
        "value":9,
        "id":735,
        "categories":[
          "Category"
        ],
        "info":"{'name_en': '麟祥南街', 'name': '麟祥南街'}"
      },
      {
        "label":"经一路",
        "value":9,
        "id":8194,
        "categories":[
          "Category"
        ],
        "info":"{'name_en': '经一路', 'name': '经一路'}"
      },
      {
        "label":"学府中央",
        "value":9,
        "id":6516,
        "categories":[
          "Category"
        ],
        "info":"{'name_en': '学府中央', 'name': '学府中央'}"
      },
      {
        "label":"大右高速公路",
        "value":9,
        "id":10486,
        "categories":[
          "Category"
        ],
        "info":"{'name_en': '大右高速公路', 'name': '大右高速公路'}"
      },
      {
        "label":"圆通街",
        "value":9,
        "id":4123,
        "categories":[
          "Category"
        ],
        "info":"{'name_en': '圆通街', 'name': '圆通街'}"
      },
      {
        "label":"南长街保护街区",
        "value":9,
        "id":7195,
        "categories":[
          "Category"
        ],
        "info":"{'name_en': '南长街保护街区', 'name': '南长街保护街区'}"
      },
      {
        "label":"坝下街",
        "value":9,
        "id":1728,
        "categories":[
          "Category"
        ],
        "info":"{'name_en': '坝下街', 'name': '坝下街'}"
      },
      {
        "label":"扇骨营",
        "value":9,
        "id":3272,
        "categories":[
          "Category"
        ],
        "info":"{'name_en': '扇骨营', 'name': '扇骨营'}"
      },
      {
        "label":"亮马桥路",
        "value":9,
        "id":7823,
        "categories":[
          "Category"
        ],
        "info":"{'name_en': '亮马桥路', 'name': '亮马桥路'}"
      },
      {
        "label":"大红门路",
        "value":9,
        "id":5082,
        "categories":[
          "Category"
        ],
        "info":"{'name_en': '大红门路', 'name': '大红门路'}"
      },
      {
        "label":"东美巷",
        "value":9,
        "id":9957,
        "categories":[
          "Category"
        ],
        "info":"{'name_en': '东美巷', 'name': '东美巷'}"
      },
      {
        "label":"济潍路",
        "value":9,
        "id":628,
        "categories":[
          "Category"
        ],
        "info":"{'name_en': '济潍路', 'name': '济潍路'}"
      },
      {
        "label":"金商汇商业街",
        "value":9,
        "id":958,
        "categories":[
          "Category"
        ],
        "info":"{'name_en': '金商汇商业街', 'name': '金商汇商业街'}"
      },
      {
        "label":"江门大道",
        "value":9,
        "id":5185,
        "categories":[
          "Category"
        ],
        "info":"{'name_en': '江门大道', 'name': '江门大道'}"
      },
      {
        "label":"桃条胡同",
        "value":9,
        "id":10828,
        "categories":[
          "Category"
        ],
        "info":"{'name_en': '桃条胡同', 'name': '桃条胡同'}"
      },
      {
        "label":"波旁街",
        "value":9,
        "id":10479,
        "categories":[
          "Category"
        ],
        "info":"{'name_en': '波旁街', 'name': '波旁街'}"
      },
      {
        "label":"郑大工学院社区",
        "value":9,
        "id":4982,
        "categories":[
          "Category"
        ],
        "info":"{'name_en': '郑大工学院社区', 'name': '郑大工学院社区'}"
      },
      {
        "label":"瞻园路",
        "value":9,
        "id":2559,
        "categories":[
          "Category"
        ],
        "info":"{'name_en': '瞻园路', 'name': '瞻园路'}"
      },
      {
        "label":"普陀路街道",
        "value":9,
        "id":3747,
        "categories":[
          "Category"
        ],
        "info":"{'name_en': '普陀路街道', 'name': '普陀路街道'}"
      },
      {
        "label":"康乐中社区",
        "value":9,
        "id":3150,
        "categories":[
          "Category"
        ],
        "info":"{'name_en': '康乐中社区', 'name': '康乐中社区'}"
      },
      {
        "label":"土库街",
        "value":9,
        "id":1439,
        "categories":[
          "Category"
        ],
        "info":"{'name_en': '土库街', 'name': '土库街'}"
      },
      {
        "label":"乙烯北路",
        "value":9,
        "id":8622,
        "categories":[
          "Category"
        ],
        "info":"{'name_en': '乙烯北路', 'name': '乙烯北路'}"
      },
      {
        "label":"云信小区",
        "value":9,
        "id":7896,
        "categories":[
          "Category"
        ],
        "info":"{'name_en': '云信小区', 'name': '云信小区'}"
      },
      {
        "label":"长岛路",
        "value":9,
        "id":3389,
        "categories":[
          "Category"
        ],
        "info":"{'name_en': '长岛路', 'name': '长岛路'}"
      },
      {
        "label":"上十八盘",
        "value":9,
        "id":3516,
        "categories":[
          "Category"
        ],
        "info":"{'name_en': '上十八盘', 'name': '上十八盘'}"
      },
      {
        "label":"后溶街社区",
        "value":9,
        "id":10520,
        "categories":[
          "Category"
        ],
        "info":"{'name_en': '后溶街社区', 'name': '后溶街社区'}"
      },
      {
        "label":"睦民社区",
        "value":9,
        "id":5409,
        "categories":[
          "Category"
        ],
        "info":"{'name_en': '睦民社区', 'name': '睦民社区'}"
      },
      {
        "label":"云绣社区",
        "value":9,
        "id":8794,
        "categories":[
          "Category"
        ],
        "info":"{'name_en': '云绣社区', 'name': '云绣社区'}"
      },
      {
        "label":"兴安里",
        "value":9,
        "id":3861,
        "categories":[
          "Category"
        ],
        "info":"{'name_en': '兴安里', 'name': '兴安里'}"
      },
      {
        "label":"薛集社区",
        "value":9,
        "id":1058,
        "categories":[
          "Category"
        ],
        "info":"{'name_en': '薛集社区', 'name': '薛集社区'}"
      },
      {
        "label":"王郢社区",
        "value":9,
        "id":373,
        "categories":[
          "Category"
        ],
        "info":"{'name_en': '王郢社区', 'name': '王郢社区'}"
      },
      {
        "label":"垦孤公路",
        "value":9,
        "id":8662,
        "categories":[
          "Category"
        ],
        "info":"{'name_en': '垦孤公路', 'name': '垦孤公路'}"
      },
      {
        "label":"永莘公路",
        "value":9,
        "id":3256,
        "categories":[
          "Category"
        ],
        "info":"{'name_en': '永莘公路', 'name': '永莘公路'}"
      },
      {
        "label":"沿河西路",
        "value":9,
        "id":8077,
        "categories":[
          "Category"
        ],
        "info":"{'name_en': '沿河西路', 'name': '沿河西路'}"
      },
      {
        "label":"峨嵋山东路",
        "value":9,
        "id":7217,
        "categories":[
          "Category"
        ],
        "info":"{'name_en': '峨嵋山东路', 'name': '峨嵋山东路'}"
      },
      {
        "label":"丝市街",
        "value":9,
        "id":5076,
        "categories":[
          "Category"
        ],
        "info":"{'name_en': '丝市街', 'name': '丝市街'}"
      },
      {
        "label":"李时珍商业步行街",
        "value":9,
        "id":3027,
        "categories":[
          "Category"
        ],
        "info":"{'name_en': '李时珍商业步行街', 'name': '李时珍商业步行街'}"
      },
      {
        "label":"人和街",
        "value":9,
        "id":5206,
        "categories":[
          "Category"
        ],
        "info":"{'name_en': '人和街', 'name': '人和街'}"
      },
      {
        "label":"乙烯南路",
        "value":9,
        "id":7817,
        "categories":[
          "Category"
        ],
        "info":"{'name_en': '乙烯南路', 'name': '乙烯南路'}"
      },
      {
        "label":"孝女路",
        "value":9,
        "id":1920,
        "categories":[
          "Category"
        ],
        "info":"{'name_en': '孝女路', 'name': '孝女路'}"
      },
      {
        "label":"吐露港公路",
        "value":9,
        "id":1917,
        "categories":[
          "Category"
        ],
        "info":"{'name_en': '吐露港公路', 'name': '吐露港公路'}"
      },
      {
        "label":"镇屐街",
        "value":9,
        "id":5912,
        "categories":[
          "Category"
        ],
        "info":"{'name_en': '镇屐街', 'name': '镇屐街'}"
      },
      {
        "label":"宁武关路",
        "value":9,
        "id":6544,
        "categories":[
          "Category"
        ],
        "info":"{'name_en': '宁武关路', 'name': '宁武关路'}"
      },
      {
        "label":"鲁宏大道",
        "value":9,
        "id":3659,
        "categories":[
          "Category"
        ],
        "info":"{'name_en': '鲁宏大道', 'name': '鲁宏大道'}"
      },
      {
        "label":"平徐公路",
        "value":9,
        "id":6630,
        "categories":[
          "Category"
        ],
        "info":"{'name_en': '平徐公路', 'name': '平徐公路'}"
      },
      {
        "label":"平阴县店子集",
        "value":9,
        "id":7272,
        "categories":[
          "Category"
        ],
        "info":"{'name_en': '平阴县店子集', 'name': '平阴县店子集'}"
      },
      {
        "label":"泰美尔",
        "value":9,
        "id":946,
        "categories":[
          "Category"
        ],
        "info":"{'name_en': '泰美尔', 'name': '泰美尔'}"
      },
      {
        "label":"文昌街",
        "value":9,
        "id":5146,
        "categories":[
          "Category"
        ],
        "info":"{'name_en': '文昌街', 'name': '文昌街'}"
      },
      {
        "label":"弄福公路",
        "value":9,
        "id":10371,
        "categories":[
          "Category"
        ],
        "info":"{'name_en': '弄福公路', 'name': '弄福公路'}"
      }
    ],
    "edges":[
      {
        "id":10423,
        "label":"街区路与国际通大街十分相似",
        "from":3172,
        "to":9434
      },
      {
        "id":10424,
        "label":"街区路和三弓路相关",
        "from":3172,
        "to":5462
      },
      {
        "id":10425,
        "label":"街区路和六条站相关",
        "from":3172,
        "to":8149
      },
      {
        "id":10426,
        "label":"街区路由黑山东区社区构成",
        "from":3172,
        "to":9270
      },
      {
        "id":10427,
        "label":"街区路和昆曼大通道相关",
        "from":3172,
        "to":3987
      },
      {
        "id":10428,
        "label":"街区路和下牛街相关",
        "from":3172,
        "to":1444
      },
      {
        "id":10429,
        "label":"街区路和徐洲新村相关",
        "from":3172,
        "to":9539
      },
      {
        "id":10430,
        "label":"街区路中包含三洞桥社区",
        "from":3172,
        "to":4860
      },
      {
        "id":10431,
        "label":"街区路和龙舟社区相关",
        "from":3172,
        "to":235
      },
      {
        "id":10432,
        "label":"街区路和桂苑城市花园相关",
        "from":3172,
        "to":8087
      },
      {
        "id":10433,
        "label":"街区路由龙霄社区构成",
        "from":3172,
        "to":1641
      },
      {
        "id":10434,
        "label":"街区路和八建线相关",
        "from":3172,
        "to":8040
      },
      {
        "id":10435,
        "label":"街区路和张家界十字街相关",
        "from":3172,
        "to":4934
      },
      {
        "id":10436,
        "label":"街区路和湖东路相关",
        "from":3172,
        "to":3095
      },
      {
        "id":10437,
        "label":"东花墙子街是一种街区路",
        "from":3172,
        "to":6400
      },
      {
        "id":10438,
        "label":"街区路和东川路相关",
        "from":3172,
        "to":1944
      },
      {
        "id":10439,
        "label":"街区路和太平北路相关",
        "from":3172,
        "to":7042
      },
      {
        "id":10440,
        "label":"街区路和风景路相关",
        "from":3172,
        "to":5104
      },
      {
        "id":10441,
        "label":"街区路和杨树浦路相关",
        "from":3172,
        "to":8056
      },
      {
        "id":10442,
        "label":"街区路和春秋大道相关",
        "from":3172,
        "to":8275
      },
      {
        "id":10443,
        "label":"街区路由机车西社区构成",
        "from":3172,
        "to":4753
      },
      {
        "id":10444,
        "label":"街区路和京通快速相关",
        "from":3172,
        "to":1955
      },
      {
        "id":10445,
        "label":"街区路和旅馆街相关",
        "from":3172,
        "to":6048
      },
      {
        "id":10446,
        "label":"街区路和九寨沟格桑宾馆相关",
        "from":3172,
        "to":9153
      },
      {
        "id":10447,
        "label":"街区路和漆咸道相关",
        "from":3172,
        "to":10923
      },
      {
        "id":10448,
        "label":"街区路由重庆磁器口明清商业街构成",
        "from":3172,
        "to":224
      },
      {
        "id":10449,
        "label":"街区路和调顺路相关",
        "from":3172,
        "to":656
      },
      {
        "id":10450,
        "label":"街区路和钟楼街相关",
        "from":3172,
        "to":8595
      },
      {
        "id":10451,
        "label":"柳市街是一种街区路",
        "from":3172,
        "to":4315
      },
      {
        "id":10452,
        "label":"街区路和双胜街相关",
        "from":3172,
        "to":1241
      },
      {
        "id":10453,
        "label":"街区路和千福巷相关",
        "from":3172,
        "to":3140
      },
      {
        "id":10454,
        "label":"街区路和戏楼胡同相关",
        "from":3172,
        "to":3169
      },
      {
        "id":10455,
        "label":"街区路由枣儿店胡同构成",
        "from":3172,
        "to":600
      },
      {
        "id":10456,
        "label":"街区路和青岛科技街相关",
        "from":3172,
        "to":3947
      },
      {
        "id":10457,
        "label":"罗布森大街是一个街区路",
        "from":3172,
        "to":6967
      },
      {
        "id":10458,
        "label":"街区路和西藏中路相关",
        "from":3172,
        "to":4989
      },
      {
        "id":10459,
        "label":"街区路途径成新蒲快速路",
        "from":3172,
        "to":6330
      },
      {
        "id":10460,
        "label":"街区路和夏悫道相关",
        "from":3172,
        "to":10909
      },
      {
        "id":10461,
        "label":"街区路中包含彩屯街道办事处",
        "from":3172,
        "to":790
      },
      {
        "id":10462,
        "label":"街区路和大厝街相关",
        "from":3172,
        "to":849
      },
      {
        "id":10463,
        "label":"街区路和鼓山路相关",
        "from":3172,
        "to":9484
      },
      {
        "id":10464,
        "label":"街区路和花街相关",
        "from":3172,
        "to":8907
      },
      {
        "id":10465,
        "label":"街区路和九谷町相关",
        "from":3172,
        "to":751
      },
      {
        "id":10466,
        "label":"街区路由包河社区构成",
        "from":3172,
        "to":7610
      },
      {
        "id":10467,
        "label":"街区路由岳化社区构成",
        "from":3172,
        "to":921
      },
      {
        "id":10468,
        "label":"戴家胡同是街区路的一部分",
        "from":3172,
        "to":4281
      },
      {
        "id":10469,
        "label":"街区路与塔前街十分相似",
        "from":3172,
        "to":2876
      },
      {
        "id":10470,
        "label":"街区路和蓬水公路相关",
        "from":3172,
        "to":7491
      },
      {
        "id":10471,
        "label":"街区路和西门岗古街相关",
        "from":3172,
        "to":7401
      },
      {
        "id":10472,
        "label":"街区路和绸市街相关",
        "from":3172,
        "to":9044
      },
      {
        "id":10473,
        "label":"街区路和淄峨路相关",
        "from":3172,
        "to":1804
      },
      {
        "id":10474,
        "label":"街区路和南三路相关",
        "from":3172,
        "to":9854
      },
      {
        "id":10475,
        "label":"街区路和夏店路相关",
        "from":3172,
        "to":9565
      },
      {
        "id":10476,
        "label":"街区路和龙王线相关",
        "from":3172,
        "to":5750
      },
      {
        "id":10477,
        "label":"街区路和济新公路相关",
        "from":3172,
        "to":6508
      },
      {
        "id":10478,
        "label":"街区路和舜玉路相关",
        "from":3172,
        "to":1678
      },
      {
        "id":10479,
        "label":"一得街是一个街区路",
        "from":3172,
        "to":10360
      },
      {
        "id":10480,
        "label":"街区路和长丰街办事处相关",
        "from":3172,
        "to":9515
      },
      {
        "id":10481,
        "label":"街区路和龙口市司法局相关",
        "from":3172,
        "to":6280
      },
      {
        "id":10482,
        "label":"街区路由中法家属院构成",
        "from":3172,
        "to":7046
      },
      {
        "id":10483,
        "label":"街区路和北15线相关",
        "from":3172,
        "to":11247
      },
      {
        "id":10484,
        "label":"街区路和北105线相关",
        "from":3172,
        "to":8778
      },
      {
        "id":10485,
        "label":"街区路和草滩社区相关",
        "from":3172,
        "to":1557
      },
      {
        "id":10486,
        "label":"街区路与井涝公路十分相似",
        "from":3172,
        "to":1356
      },
      {
        "id":10487,
        "label":"街区路和大李公路相关",
        "from":3172,
        "to":1591
      },
      {
        "id":10488,
        "label":"街区路和东康庄公路相关",
        "from":3172,
        "to":765
      },
      {
        "id":10489,
        "label":"街区路和成贤街相关",
        "from":3172,
        "to":3341
      },
      {
        "id":10490,
        "label":"街区路与沙丘路十分相似",
        "from":3172,
        "to":6115
      },
      {
        "id":10491,
        "label":"街区路和白虎山西路相关",
        "from":3172,
        "to":6001
      },
      {
        "id":10492,
        "label":"街区路和棉花市街相关",
        "from":3172,
        "to":7744
      },
      {
        "id":10493,
        "label":"街区路和章索公路相关",
        "from":3172,
        "to":3192
      },
      {
        "id":10494,
        "label":"街区路和香同公路相关",
        "from":3172,
        "to":1126
      },
      {
        "id":10495,
        "label":"街区路与花苑街十分相似",
        "from":3172,
        "to":9915
      },
      {
        "id":10496,
        "label":"街区路和谷物市场街相关",
        "from":3172,
        "to":11131
      },
      {
        "id":10497,
        "label":"街区路和北大屿山公路相关",
        "from":3172,
        "to":1248
      },
      {
        "id":10498,
        "label":"街区路和对关街相关",
        "from":3172,
        "to":3
      },
      {
        "id":10499,
        "label":"街区路和麟祥南街相关",
        "from":3172,
        "to":735
      },
      {
        "id":10500,
        "label":"街区路和经一路相关",
        "from":3172,
        "to":8194
      },
      {
        "id":10501,
        "label":"街区路和学府中央相关",
        "from":3172,
        "to":6516
      },
      {
        "id":10502,
        "label":"街区路与大右高速公路十分相似",
        "from":3172,
        "to":10486
      },
      {
        "id":10503,
        "label":"街区路和圆通街相关",
        "from":3172,
        "to":4123
      },
      {
        "id":10504,
        "label":"街区路由南长街保护街区构成",
        "from":3172,
        "to":7195
      },
      {
        "id":10505,
        "label":"街区路和坝下街相关",
        "from":3172,
        "to":1728
      },
      {
        "id":10506,
        "label":"街区路和扇骨营相关",
        "from":3172,
        "to":3272
      },
      {
        "id":10507,
        "label":"街区路和亮马桥路相关",
        "from":3172,
        "to":7823
      },
      {
        "id":10508,
        "label":"街区路和大红门路相关",
        "from":3172,
        "to":5082
      },
      {
        "id":10509,
        "label":"街区路和东美巷相关",
        "from":3172,
        "to":9957
      },
      {
        "id":10510,
        "label":"街区路和济潍路相关",
        "from":3172,
        "to":628
      },
      {
        "id":10511,
        "label":"金商汇商业街是一个街区路",
        "from":3172,
        "to":958
      },
      {
        "id":10512,
        "label":"街区路和江门大道相关",
        "from":3172,
        "to":5185
      },
      {
        "id":10513,
        "label":"街区路和桃条胡同相关",
        "from":3172,
        "to":10828
      },
      {
        "id":10514,
        "label":"街区路途径波旁街",
        "from":3172,
        "to":10479
      },
      {
        "id":10515,
        "label":"街区路由郑大工学院社区构成",
        "from":3172,
        "to":4982
      },
      {
        "id":10516,
        "label":"街区路和瞻园路相关",
        "from":3172,
        "to":2559
      },
      {
        "id":10517,
        "label":"街区路中包含普陀路街道",
        "from":3172,
        "to":3747
      },
      {
        "id":10518,
        "label":"街区路由康乐中社区构成",
        "from":3172,
        "to":3150
      },
      {
        "id":10519,
        "label":"街区路和土库街相关",
        "from":3172,
        "to":1439
      },
      {
        "id":10520,
        "label":"街区路和乙烯北路相关",
        "from":3172,
        "to":8622
      },
      {
        "id":10521,
        "label":"街区路由云信小区构成",
        "from":3172,
        "to":7896
      },
      {
        "id":10522,
        "label":"街区路和长岛路相关",
        "from":3172,
        "to":3389
      },
      {
        "id":10523,
        "label":"街区路和上十八盘相关",
        "from":3172,
        "to":3516
      },
      {
        "id":10524,
        "label":"街区路由后溶街社区构成",
        "from":3172,
        "to":10520
      },
      {
        "id":10525,
        "label":"街区路由睦民社区构成",
        "from":3172,
        "to":5409
      },
      {
        "id":10526,
        "label":"街区路由云绣社区构成",
        "from":3172,
        "to":8794
      },
      {
        "id":10527,
        "label":"兴安里是街区路的一部分",
        "from":3172,
        "to":3861
      },
      {
        "id":10528,
        "label":"街区路由薛集社区构成",
        "from":3172,
        "to":1058
      },
      {
        "id":10529,
        "label":"街区路由王郢社区构成",
        "from":3172,
        "to":373
      },
      {
        "id":10530,
        "label":"街区路和垦孤公路相关",
        "from":3172,
        "to":8662
      },
      {
        "id":10531,
        "label":"街区路和永莘公路相关",
        "from":3172,
        "to":3256
      },
      {
        "id":10532,
        "label":"街区路和沿河西路相关",
        "from":3172,
        "to":8077
      },
      {
        "id":10533,
        "label":"街区路和峨嵋山东路相关",
        "from":3172,
        "to":7217
      },
      {
        "id":10534,
        "label":"街区路和丝市街相关",
        "from":3172,
        "to":5076
      },
      {
        "id":10535,
        "label":"李时珍商业步行街是一个街区路",
        "from":3172,
        "to":3027
      },
      {
        "id":10536,
        "label":"街区路和人和街相关",
        "from":3172,
        "to":5206
      },
      {
        "id":10537,
        "label":"街区路和乙烯南路相关",
        "from":3172,
        "to":7817
      },
      {
        "id":10538,
        "label":"街区路和孝女路相关",
        "from":3172,
        "to":1920
      },
      {
        "id":10539,
        "label":"街区路途径吐露港公路",
        "from":3172,
        "to":1917
      },
      {
        "id":10540,
        "label":"街区路与镇屐街十分相似",
        "from":3172,
        "to":5912
      },
      {
        "id":10541,
        "label":"街区路和宁武关路相关",
        "from":3172,
        "to":6544
      },
      {
        "id":10542,
        "label":"街区路和鲁宏大道相关",
        "from":3172,
        "to":3659
      },
      {
        "id":10543,
        "label":"街区路和平徐公路相关",
        "from":3172,
        "to":6630
      },
      {
        "id":10544,
        "label":"街区路和平阴县店子集相关",
        "from":3172,
        "to":7272
      },
      {
        "id":10545,
        "label":"街区路和泰美尔相关",
        "from":3172,
        "to":946
      },
      {
        "id":10546,
        "label":"街区路和文昌街相关",
        "from":3172,
        "to":5146
      },
      {
        "id":10547,
        "label":"街区路和弄福公路相关",
        "from":3172,
        "to":10371
      }
    ]
  }
}